{"product_tile": "O General FUT Series 2 Ton 3 Star Split AC (2021 Model, Copper Condenser, Dust Filter, ASGA24FUTC)", "mrp": null, "product_price": null, "key_features": ["2 Ton, 3 Star Rating", "Copper Condenser", "1 Year Comprehensive Warranty, 5 Years Compressor Warranty", "For Rooms up to 240 sqft", "Power Consumption: 2070 Watts", "Refrigerant: R410A", "Coanda Airflow Technology, Self Diagnosis", "2 Ton, 3 Star Rating", "Copper Condenser", "1 Year Comprehensive Warranty, 5 Years Compressor Warranty", "For Rooms up to 240 sqft", "Power Consumption: 2070 Watts", "Refrigerant: R410A", "Coanda Airflow Technology, Self Diagnosis"], "specifications": [{"specification_key": "Air Conditioner Type", "specification_value": "Split"}, {"specification_key": "Air Conditioner Capacity", "specification_value": "2 Ton"}, {"specification_key": "Approximate Coverage Area(Sq.Ft)", "specification_value": "240 Sq. Ft."}, {"specification_key": "Approximate Coverage Area(Sq.M)", "specification_value": "22.3 Sq.m"}, {"specification_key": "Installation Type", "specification_value": "Wall Mount"}, {"specification_key": "Brand", "specification_value": "O General"}, {"specification_key": "Model Series", "specification_value": "ASGA24FUTC"}, {"specification_key": "Model Number", "specification_value": "ASGA24FUTC"}, {"specification_key": "Convertible Mode", "specification_value": "No"}, {"specification_key": "Air Flow Volume", "specification_value": "IDU: 871 (In) CFM"}, {"specification_key": "Inverter Technology", "specification_value": "No"}, {"specification_key": "Cooling Capacity", "specification_value": "Rated Capacity - 7250 Watts"}, {"specification_key": "Ambient Temperature (Cooling/Heating) In Degree Celsius", "specification_value": "Cooling - 52"}, {"specification_key": "Running Current (Cooling/Heating)InAmps", "specification_value": "Cooling: 9.31"}, {"specification_key": "Cooling Power Input", "specification_value": "Rated Input - 2070 Watts"}, {"specification_key": "Additional Air Conditioner Features", "specification_value": "Self Diagnosis  | Moisture Removal: 2.0 Ltr/Hr"}, {"specification_key": "Compressor Type", "specification_value": "Hyper Tropical Rotary Compressor"}, {"specification_key": "Refrigerant Type", "specification_value": "R-410a"}, {"specification_key": "Noise Level (Indoor Unit)", "specification_value": "35 dB"}, {"specification_key": "Noise Level (Outdoor Unit)", "specification_value": "55 dB"}, {"specification_key": "Air Flow Type", "specification_value": "Coanda Air Flow"}, {"specification_key": "Additional Air Conditioner Functions", "specification_value": "Indoor Airflow Distance - 20 Metre  | Double swing automatic 3D  | Quiet Operation  | Electricity Consumption: 1603 Units/Year"}, {"specification_key": "Connecting Pipe Type", "specification_value": "Copper Pipe"}, {"specification_key": "Condenser Coil Type", "specification_value": "Copper Condenser"}, {"specification_key": "Louvers Swing Type", "specification_value": "Up/Down"}, {"specification_key": "Other Body Features", "specification_value": "Dual Suction Intake Design  | Condenser: Blue Fin"}, {"specification_key": "Energy Efficiency(Star Rating)", "specification_value": "3 Star"}, {"specification_key": "Energy Efficiency Ratio (EER)", "specification_value": "3.50"}, {"specification_key": "Indian Seasonal Energy Efficiency Ratio (ISEER)", "specification_value": "3.50"}, {"specification_key": "Power", "specification_value": "1002 W"}, {"specification_key": "Voltage Rating", "specification_value": "230 V"}, {"specification_key": "Frequency", "specification_value": "50 Hz"}, {"specification_key": "Phase", "specification_value": "Single"}, {"specification_key": "Color", "specification_value": "White"}, {"specification_key": "Color Family", "specification_value": "White"}, {"specification_key": "Generic Name", "specification_value": "Air Conditioner"}, {"specification_key": "Main Product", "specification_value": "1  U Indoor Unit & Outdoor Unit"}, {"specification_key": "Accessories", "specification_value": "Wall-Mount Kit  | Remote Control Battery  | Remote Control  | Remote  | Wall Mount"}, {"specification_key": "Documents", "specification_value": "Safety and Warranty Documents  | Warranty Card  | User Manual  | User Manual"}, {"specification_key": "Dimensions in cm (WxDxH)", "specification_value": "109.8x42x117"}, {"specification_key": "Dimensions in Inches (WxDxH)", "specification_value": "45.28 x 11.02 x 13.39"}, {"specification_key": "Weight", "specification_value": "17000 g"}, {"specification_key": "Depth", "specification_value": "11.02 Inches"}, {"specification_key": "Width", "specification_value": "45.28 Inches"}, {"specification_key": "Height", "specification_value": "13.39 Inches"}, {"specification_key": "Weight", "specification_value": "17 kg"}, {"specification_key": "Dimensions in cm (WxDxH)", "specification_value": "83 x 32 x 65"}, {"specification_key": "Dimensions in Inches (WxDxH)", "specification_value": "32.68 x 12.6 x 25.59"}, {"specification_key": "Weight", "specification_value": "52.01 kg"}, {"specification_key": "Standard Warranty Period", "specification_value": "12 Months"}, {"specification_key": "Additional Warranties", "specification_value": "1 Year Warranty On Condenser | 5 Years Warranty On Compressor"}, {"specification_key": "Installation & Demo", "specification_value": "Croma will coordinate with the brand for Installation and Demo"}, {"specification_key": "Manufacturer/Importer/Marketer Name & Address", "specification_value": "Manufacturer Name & Address: ETA General Pvt. Ltd. ETA House 3rd Floor #71/63 Opp.Loyola College Sterling Road Nungambakkam Chennai - 6000034 Tamilnadu.  | Marketer Name & Address: ETA General Pvt. Ltd. ETA House 3rd Floor #71/63 Opp.Loyola College Sterling Road Nungambakkam Chennai - 6000034 Tamilnadu."}, {"specification_key": "Brand Support Number", "specification_value": "18602081007 | 6379881007"}, {"specification_key": "Brand Support Email", "specification_value": "customercare@etageneral.com"}, {"specification_key": "Country of Manufacture", "specification_value": "Thailand"}, {"specification_key": "Country of Brand Origin", "specification_value": "Japan"}, {"specification_key": "Customer Care Contact Person", "specification_value": "Grievance Officer"}, {"specification_key": "Registered Name and Address", "specification_value": "Infiniti Retail Ltd. - Unit No. 701 & 702, 7th Floor, Kaledonia, Sahar Road, Andheri (East); Mumbai - 400069. India"}, {"specification_key": "Customer Support Number", "specification_value": "1800-57-27662"}]}