{"product_tile": "Daikin Standard Plus 1.5 Ton 3 Star Inverter Split AC (Copper Condenser, Dew Clean Technology, MTKL50U)", "mrp": null, "product_price": null, "key_features": ["1.5 Ton Inverter AC, 3 Star Rating", "Copper Condenser", "1 Year Comprehensive Warranty, 10 Years Compressor Warranty", "For Rooms up to 180 sqft", "Power Consumption: 1670 Watts", "Refrigerant: R32", "PM 2.5 Filter, TAD Air Purification Filter", "1.5 Ton Inverter AC, 3 Star Rating", "Copper Condenser", "1 Year Comprehensive Warranty, 10 Years Compressor Warranty", "For Rooms up to 180 sqft", "Power Consumption: 1670 Watts", "Refrigerant: R32", "PM 2.5 Filter, TAD Air Purification Filter"], "specifications": [{"specification_key": "Air Conditioner Type", "specification_value": "Split"}, {"specification_key": "Air Conditioner Capacity", "specification_value": "1.5 Ton"}, {"specification_key": "Approximate Coverage Area(Sq.Ft)", "specification_value": "180 Sq. Ft."}, {"specification_key": "Approximate Coverage Area(Sq.M)", "specification_value": "16.72 Sq.m"}, {"specification_key": "Installation Type", "specification_value": "Wall Mount"}, {"specification_key": "Brand", "specification_value": "Daikin"}, {"specification_key": "Model Series", "specification_value": "Standard Plus"}, {"specification_key": "Model Number", "specification_value": "MTKL50U"}, {"specification_key": "Air Conditioner Modes", "specification_value": "Sleep Mode"}, {"specification_key": "Convertible Mode", "specification_value": "No"}, {"specification_key": "Cooling Technology", "specification_value": "Fast Cooling"}, {"specification_key": "Air Flow Volume", "specification_value": "572 CFM"}, {"specification_key": "Humidity Control", "specification_value": "Yes"}, {"specification_key": "Inverter Technology", "specification_value": "Yes"}, {"specification_key": "Cooling Capacity", "specification_value": "Full: 5000 Watts, Half: 2500 Watts (Minimum: 1900 Watts, Maximum: 5200 Watts)"}, {"specification_key": "Ambient Temperature (Cooling/Heating) In Degree Celsius", "specification_value": "20 - 52 Degree Celsius"}, {"specification_key": "Running Current (Cooling/Heating)InAmps", "specification_value": "7.64 Amps"}, {"specification_key": "Additional Air Conditioner Features", "specification_value": "Annual Power Consumption: 966.47 kWh  | Built-in Stabilizer (Voltage Free Operation Level: 130 - 265V)  | Dehumidifier, Power Chill Operation  | Air Throw Distance: 16 Meters (52 Feet)  | Display Options: Power Consumption Percentage, Set Per Room Temperature, Auto Error Code"}, {"specification_key": "Compressor Type", "specification_value": "Neo Swing Compressor"}, {"specification_key": "Refrigerant Type", "specification_value": "R-32"}, {"specification_key": "Air Conditioner Filters", "specification_value": "PM 2.5 Filter, Dust Filter"}, {"specification_key": "Air Flow Type", "specification_value": "3D Air Flow"}, {"specification_key": "Air Purification Function", "specification_value": "Yes"}, {"specification_key": "Air Purification Type", "specification_value": "Titanium Apatite Deodorizer"}, {"specification_key": "Additional Air Conditioner Functions", "specification_value": "Noise Level: 45, 42, 40, 38, 35, 32 dBA"}, {"specification_key": "Connecting Pipe Type", "specification_value": "Copper Connecting Pipe"}, {"specification_key": "Connecting Pipe Length", "specification_value": "3 m"}, {"specification_key": "Condenser Coil Type", "specification_value": "Copper Condenser Coil"}, {"specification_key": "Louvers Swing Type", "specification_value": "Up/Down Automatic  | Left/Right Automatic"}, {"specification_key": "Other Body Features", "specification_value": "Moisture Removal: 1.6 Litres Per Hour  | Breaker Size: 20A  | Piping Connection: 0.5 Inch (Gas), 0.25 Inch (Liquid)"}, {"specification_key": "Additional Smart Functions", "specification_value": "Auto Clean  | Smart Diagnosis"}, {"specification_key": "Type", "specification_value": "Triple Display"}, {"specification_key": "WiFi Features", "specification_value": "Wifi Ready"}, {"specification_key": "Additional Technology Supported", "specification_value": "Dew Clean Technology"}, {"specification_key": "Energy Efficiency(Star Rating)", "specification_value": "3 Star"}, {"specification_key": "Power", "specification_value": "1670 W"}, {"specification_key": "Voltage Rating", "specification_value": "230V"}, {"specification_key": "Frequency", "specification_value": "50 Hz"}, {"specification_key": "Phase", "specification_value": "Single Phase"}, {"specification_key": "Color", "specification_value": "White"}, {"specification_key": "Color Family", "specification_value": "White"}, {"specification_key": "Generic Name", "specification_value": "Air Conditioner"}, {"specification_key": "Main Product", "specification_value": "1  U Indoor Unit & Outdoor Unit"}, {"specification_key": "Accessories", "specification_value": "Remote Control"}, {"specification_key": "Documents", "specification_value": "Warranty Card  | User Manual"}, {"specification_key": "Dimensions in cm (WxDxH)", "specification_value": "94.5x40x69.5"}, {"specification_key": "Dimensions in Inches (WxDxH)", "specification_value": "34.84 x 9.02 x 11.73"}, {"specification_key": "Weight", "specification_value": "10.5 kg"}, {"specification_key": "Dimensions in cm (WxDxH)", "specification_value": "84.50 x 30.00 x 59.50"}, {"specification_key": "Dimensions in Inches (WxDxH)", "specification_value": "33.27 x 11.81 x 23.43"}, {"specification_key": "Weight", "specification_value": "28 kg"}, {"specification_key": "Dimensions in cm (WxDxH)", "specification_value": "98.00 x 32.50 x 37.50"}, {"specification_key": "Dimensions in Inches (WxDxH)", "specification_value": "38.58 x 12.8 x 14.76"}, {"specification_key": "Weight", "specification_value": "13.5 kg"}, {"specification_key": "Dimensions in cm (WxDxH)", "specification_value": "103.50 x 41.00 x 68.00"}, {"specification_key": "Dimensions in Inches (WxDxH)", "specification_value": "40.75 x 16.14 x 26.77"}, {"specification_key": "Weight", "specification_value": "33 kg"}, {"specification_key": "Standard Warranty Period", "specification_value": "12 Months"}, {"specification_key": "Additional Warranties", "specification_value": "1 Year Warranty on Condenser| 10 Years Warranty on Compressor"}, {"specification_key": "Warranty Type", "specification_value": "Onsite"}, {"specification_key": "Installation & Demo", "specification_value": "Croma will coordinate for Installation and Demo on Chargeable Basis"}, {"specification_key": "Manufacturer/Importer/Marketer Name & Address", "specification_value": "Manufacturer Name & Address: Daikin Airconditioning India Pvt. Ltd. | 210, 1st Floor, Okhla Industrial Area, Phase 3, Delhi 110020"}, {"specification_key": "Brand Support Number", "specification_value": "9824502178"}, {"specification_key": "Brand Support Email", "specification_value": "customerservice@daikinindia.com"}, {"specification_key": "Country of Manufacture", "specification_value": "India"}, {"specification_key": "Country of Brand Origin", "specification_value": "Japan"}, {"specification_key": "Customer Care Contact Person", "specification_value": "Grievance Officer"}, {"specification_key": "Registered Name and Address", "specification_value": "Infiniti Retail Ltd. - Unit No. 701 & 702, 7th Floor, Kaledonia, Sahar Road, Andheri (East); Mumbai - 400069. India"}, {"specification_key": "Customer Support Number", "specification_value": "1800-57-27662"}, {"specification_key": "Customer Support Email", "specification_value": "customersupport@croma.com"}]}